[1,["01OWZohONHBLEecUJDeG8m"],0,[["sp.SkeletonData",["_name","_atlasText","textureNames","_skeletonJson","textures"],-1,3]],[[0,0,1,2,3,4,5]],[[0,"Character 20","\r\nCharacter 20.png\r\nsize: 1616,340\r\nformat: RGBA8888\r\nfilter: Linear,Linear\r\nrepeat: none\r\nban chan p\r\n  rotate: true\r\n  xy: 1452, 99\r\n  size: 81, 39\r\n  orig: 81, 39\r\n  offset: 0, 0\r\n  index: -1\r\nban chan t\r\n  rotate: true\r\n  xy: 1452, 17\r\n  size: 80, 39\r\n  orig: 80, 39\r\n  offset: 0, 0\r\n  index: -1\r\nban tay p\r\n  rotate: true\r\n  xy: 966, 5\r\n  size: 66, 84\r\n  orig: 66, 84\r\n  offset: 0, 0\r\n  index: -1\r\nban tay t\r\n  rotate: true\r\n  xy: 1214, 20\r\n  size: 66, 85\r\n  orig: 66, 85\r\n  offset: 0, 0\r\n  index: -1\r\ncao quang\r\n  rotate: false\r\n  xy: 1301, 65\r\n  size: 15, 21\r\n  orig: 15, 21\r\n  offset: 0, 0\r\n  index: -1\r\ncao quang Copy\r\n  rotate: false\r\n  xy: 1301, 42\r\n  size: 15, 21\r\n  orig: 15, 21\r\n  offset: 0, 0\r\n  index: -1\r\nchan p\r\n  rotate: 180\r\n  xy: 1554, 221\r\n  size: 58, 92\r\n  orig: 58, 92\r\n  offset: 0, 0\r\n  index: -1\r\nchan t\r\n  rotate: 180\r\n  xy: 1548, 4\r\n  size: 59, 92\r\n  orig: 59, 92\r\n  offset: 0, 0\r\n  index: -1\r\ndau\r\n  rotate: false\r\n  xy: 381, 16\r\n  size: 376, 322\r\n  orig: 376, 322\r\n  offset: 0, 0\r\n  index: -1\r\ndau1\r\n  rotate: false\r\n  xy: 2, 16\r\n  size: 377, 322\r\n  orig: 377, 322\r\n  offset: 0, 0\r\n  index: -1\r\neye_L\r\n  rotate: false\r\n  xy: 1319, 182\r\n  size: 131, 156\r\n  orig: 131, 156\r\n  offset: 0, 0\r\n  index: -1\r\neye_L1\r\n  rotate: false\r\n  xy: 1052, 3\r\n  size: 45, 67\r\n  orig: 45, 67\r\n  offset: 0, 0\r\n  index: -1\r\neye_R\r\n  rotate: false\r\n  xy: 1319, 24\r\n  size: 131, 156\r\n  orig: 131, 156\r\n  offset: 0, 0\r\n  index: -1\r\neye_R1\r\n  rotate: false\r\n  xy: 1452, 182\r\n  size: 43, 68\r\n  orig: 43, 68\r\n  offset: 0, 0\r\n  index: -1\r\nlong den p\r\n  rotate: false\r\n  xy: 1527, 163\r\n  size: 38, 55\r\n  orig: 38, 55\r\n  offset: 0, 0\r\n  index: -1\r\nlong den t\r\n  rotate: false\r\n  xy: 1523, 220\r\n  size: 38, 55\r\n  orig: 38, 55\r\n  offset: 0, 0\r\n  index: -1\r\nlong may p\r\n  rotate: false\r\n  xy: 1501, 277\r\n  size: 49, 42\r\n  orig: 49, 42\r\n  offset: 0, 0\r\n  index: -1\r\nlong may t\r\n  rotate: true\r\n  xy: 1493, 92\r\n  size: 57, 45\r\n  orig: 57, 45\r\n  offset: 0, 0\r\n  index: -1\r\nmieng\r\n  rotate: true\r\n  xy: 1159, 88\r\n  size: 250, 158\r\n  orig: 250, 158\r\n  offset: 0, 0\r\n  index: -1\r\nmieng 1\r\n  rotate: true\r\n  xy: 759, 16\r\n  size: 321, 205\r\n  orig: 321, 205\r\n  offset: 0, 0\r\n  index: -1\r\ntay p\r\n  rotate: 180\r\n  xy: 1452, 151\r\n  size: 73, 167\r\n  orig: 73, 167\r\n  offset: 0, 0\r\n  index: -1\r\ntay t\r\n  rotate: false\r\n  xy: 1492, 8\r\n  size: 78, 155\r\n  orig: 78, 155\r\n  offset: 0, 0\r\n  index: -1\r\nthan\r\n  rotate: false\r\n  xy: 966, 72\r\n  size: 191, 266\r\n  orig: 191, 266\r\n  offset: 0, 0\r\n  index: -1\r\ntoc\r\n  rotate: false\r\n  xy: 1099, 8\r\n  size: 113, 78\r\n  orig: 113, 78\r\n  offset: 0, 0\r\n  index: -1\r\n",["Character 20.png"],{"skeleton":{"hash":"HX4oRzINAMjNbASO1/8wOgDpYf0","spine":"3.8.99","x":-200.54,"y":-8.99,"width":376,"height":682,"images":"./images/","audio":"E:/KYX 2021/PENCIL MAN/20_gay rang"},"bones":[{"name":"root"},{"name":"bone","parent":"root","length":176.54,"rotation":91.68,"x":-4.5,"y":107.25},{"name":"dau","parent":"bone","x":209.52,"y":1.38},{"name":"tay p","parent":"bone","length":89.33,"rotation":141.68,"x":165.78,"y":72.04},{"name":"tay p2","parent":"tay p","length":82.91,"rotation":35.09,"x":89.33},{"name":"ban tay p","parent":"tay p2","length":49.41,"rotation":-2.61,"x":80.7,"y":-0.96},{"name":"tay t","parent":"bone","length":88.17,"rotation":-145.57,"x":165.34,"y":-64.65},{"name":"tay t2","parent":"tay t","length":70.41,"rotation":-26.59,"x":88.17},{"name":"ban tay t","parent":"tay t2","length":45.57,"rotation":-2.75,"x":71.15,"y":-1.03},{"name":"chan p","parent":"bone","length":59.9,"rotation":128.18,"x":1.62,"y":51.83},{"name":"chan p2","parent":"chan p","length":61.45,"rotation":91.7,"x":59.9},{"name":"ban chan p","parent":"chan p2","length":49.68,"rotation":-116.07,"x":63.18,"y":-0.9},{"name":"chan t","parent":"bone","length":64.19,"rotation":-129.49,"x":-0.55,"y":-54.33},{"name":"chan t2","parent":"chan t","length":60.42,"rotation":-94.02,"x":64.19},{"name":"ban chan t","parent":"chan t2","length":63.36,"rotation":116.64,"x":59.75,"y":0.04},{"name":"mieng","parent":"dau","x":9.88,"y":-5.12},{"name":"eye_R","parent":"dau","x":163.05,"y":59.14},{"name":"eye_L","parent":"dau","x":157.85,"y":-82.21},{"name":"chan_p","parent":"root","x":-61.11,"y":21.84,"color":"ff3f00ff"},{"name":"chan t3","parent":"root","x":61.2,"y":26.83,"color":"ff3f00ff"},{"name":"mui chan t","parent":"chan t3","x":60.54,"y":-17.99,"color":"ff3f00ff"},{"name":"mui chan p","parent":"chan_p","x":-46.49,"y":-13.82,"color":"ff3f00ff"},{"name":"eye_R2","parent":"eye_R","x":-26.41,"y":-12.71},{"name":"eye_L2","parent":"eye_L","x":-26.94,"y":20.14},{"name":"eye_L3","parent":"eye_L","x":130.76,"y":33.44},{"name":"eye_R3","parent":"eye_R","x":145.19,"y":8.9},{"name":"dau2","parent":"dau","length":61.15,"rotation":-1.04,"x":227.72,"y":-9.03}],"slots":[{"name":"than","bone":"bone","attachment":"than"},{"name":"tay t","bone":"tay t","attachment":"tay t"},{"name":"ban tay t","bone":"ban tay t","attachment":"ban tay t"},{"name":"ban tay p","bone":"ban tay p","attachment":"ban tay p"},{"name":"tay p","bone":"tay p","attachment":"tay p"},{"name":"chan p","bone":"chan p","attachment":"chan p"},{"name":"ban chan p","bone":"ban chan p","attachment":"ban chan p"},{"name":"ban chan t","bone":"ban chan t","attachment":"ban chan t"},{"name":"chan t","bone":"chan t","attachment":"chan t"},{"name":"dau","bone":"dau","attachment":"dau"},{"name":"mieng","bone":"mieng","attachment":"mieng"},{"name":"eye_R","bone":"eye_R","attachment":"eye_R"},{"name":"long den p","bone":"eye_R2","attachment":"long den p"},{"name":"cao quang","bone":"eye_R2","attachment":"cao quang"},{"name":"eye_L","bone":"eye_L","attachment":"eye_L"},{"name":"long den t","bone":"eye_L2","attachment":"long den t"},{"name":"cao quang Copy","bone":"eye_L2","attachment":"cao quang Copy"},{"name":"long may p","bone":"eye_R3","attachment":"long may p"},{"name":"long may t","bone":"eye_L3","attachment":"long may t"},{"name":"toc","bone":"dau2","attachment":"toc"}],"ik":[{"name":"chan_p","target":"chan_p","bones":["chan p","chan p2"]},{"name":"chan t","order":1,"target":"chan t3","bendPositive":false,"bones":["chan t","chan t2"]},{"name":"mui chan p","order":3,"target":"mui chan p","bones":["ban chan p"]},{"name":"mui chan t","order":2,"target":"mui chan t","bones":["ban chan t"]}],"skins":[{"name":"default","attachments":{"ban chan p":{"ban chan p":{"x":27.44,"y":1.86,"rotation":164.51,"width":81,"height":39}},"ban chan t":{"ban chan t":{"x":29.69,"y":0.34,"rotation":15.18,"width":80,"height":39}},"ban tay p":{"ban tay p":{"x":34.17,"y":-0.23,"rotation":94.16,"width":66,"height":84}},"ban tay t":{"ban tay t":{"x":33.32,"y":1.57,"rotation":83.22,"width":66,"height":85}},"cao quang":{"cao quang":{"x":-13.87,"y":0.98,"rotation":-91.68,"width":15,"height":21}},"cao quang Copy":{"cao quang Copy":{"x":-11.42,"y":-1.48,"rotation":-91.68,"width":15,"height":21}},"chan p":{"chan p":{"type":"mesh","hull":34,"width":58,"height":92,"uvs":[0.82058,0.00746,0.93337,0.00696,0.98811,0.04165,0.98818,0.08801,0.9616,0.12148,0.60623,0.22628,0.54251,0.24994,0.39727,0.32298,0.29249,0.37567,0.2555,0.43782,0.21283,0.5095,0.24868,0.55503,0.31522,0.63953,0.37792,0.6791,0.44826,0.72348,0.58497,0.78271,0.71697,0.83991,0.78151,0.86787,0.81534,0.88947,0.83605,0.92932,0.81329,0.97319,0.77112,0.99265,0.6858,0.9925,0.58979,0.96112,0.45158,0.90014,0.34697,0.85399,0.22162,0.77516,0.10078,0.69918,0.01173,0.59003,0.01141,0.5046,0.01099,0.39213,0.07822,0.30464,0.26382,0.18729,0.53833,0.08375],"triangles":[9,10,30,10,29,30,8,9,31,9,30,31,7,8,32,8,31,32,7,32,6,5,6,33,3,4,0,4,5,0,6,32,33,5,33,0,3,1,2,1,3,0,20,21,19,21,22,19,22,23,17,19,22,18,18,22,17,23,24,16,23,16,17,16,24,15,24,25,15,25,14,15,14,26,13,14,25,26,26,12,13,26,27,12,27,11,12,27,28,11,28,10,11,28,29,10],"vertices":[2,10,10.45,94.91,0.09409,9,-34.89,8.53,0.90591,2,10,14.76,99.83,0.06717,9,-39.94,12.69,0.93283,2,10,19.25,100.09,0.05638,9,-40.33,17.18,0.94362,2,10,22.45,97.27,0.0615,9,-37.6,20.45,0.9385,2,10,23.73,94.07,0.08285,9,-34.44,21.83,0.91715,2,10,1.49,37.38,0.12106,9,22.49,0.38,0.87894,2,10,0.67,33.17,0.16577,9,26.73,-0.32,0.83423,2,10,0.11,22.41,0.22738,9,37.5,-0.56,0.77262,2,10,-0.3,14.64,0.31654,9,45.27,-0.73,0.68346,2,10,2.56,9.25,0.42231,9,50.58,2.28,0.57769,2,10,5.85,3.02,0.53525,9,56.71,5.76,0.46475,2,10,10.36,1.8,0.64578,9,57.8,10.31,0.35422,2,10,18.74,-0.47,0.74539,9,59.82,18.75,0.25461,2,10,23.88,-0.17,0.82812,9,59.36,23.87,0.17188,2,10,29.64,0.18,0.8914,9,58.85,29.62,0.1086,2,10,38.98,2.5,0.93586,9,56.25,38.89,0.06414,2,10,47.99,4.73,0.96419,9,53.75,47.83,0.03581,2,10,52.4,5.83,0.97926,9,52.52,52.21,0.02074,2,10,55.19,5.98,0.98744,9,52.29,54.99,0.01256,2,10,58.73,4.44,0.99239,9,53.72,58.57,0.00761,2,10,60.87,0.78,0.99338,9,57.32,60.82,0.00662,2,10,60.59,-2.24,0.9907,9,60.34,60.63,0.0093,2,10,57.3,-5.93,0.98372,9,64.13,57.45,0.01628,2,10,51.44,-8.18,0.96528,9,66.56,51.66,0.03472,2,10,41.93,-10.46,0.93612,9,69.12,42.22,0.06388,2,10,34.73,-12.18,0.89146,9,71.05,35.07,0.10854,2,10,24.48,-12.81,0.82813,9,71.98,24.84,0.17187,2,10,14.6,-13.42,0.74539,9,72.88,14.99,0.25461,2,10,3.66,-10.62,0.64575,9,70.41,3.97,0.35425,2,10,-2.24,-5.42,0.53511,9,65.39,-2.08,0.46489,2,10,-10,1.42,0.42179,9,58.77,-10.03,0.57821,2,10,-13.43,9.68,0.31455,9,50.62,-13.71,0.68545,2,10,-14.37,24.9,0.21987,9,35.44,-15.1,0.78013,2,10,-10.93,43.13,0.13758,9,17.11,-12.21,0.86242],"edges":[0,66,0,2,2,4,4,6,6,8,8,10,10,12,34,36,36,38,38,40,40,42,42,44,44,46,54,56,60,62,62,64,64,66,10,66,12,14,14,16,64,14,16,62,16,18,18,20,18,60,56,58,58,60,20,58,20,22,22,24,56,22,54,24,24,26,26,28,50,52,52,54,26,52,28,50,28,30,46,48,48,50,30,48,30,32,32,34,46,32,36,44]}},"chan t":{"chan t":{"type":"mesh","hull":41,"width":59,"height":92,"uvs":[0.15469,0.00718,0.27731,0.03628,0.38808,0.07167,0.54936,0.1232,0.61463,0.14405,0.76742,0.21362,0.87668,0.28489,0.94131,0.32704,0.98836,0.39891,0.9886,0.48444,0.98894,0.6033,0.89394,0.7032,0.78591,0.77259,0.66621,0.84947,0.56161,0.8944,0.43926,0.94695,0.38764,0.96912,0.30563,0.99267,0.21719,0.99251,0.1635,0.95756,0.16402,0.90043,0.2126,0.86846,0.27362,0.8431,0.32364,0.8223,0.41745,0.7833,0.55135,0.72764,0.61522,0.68712,0.68608,0.64216,0.75438,0.55242,0.80038,0.49198,0.77357,0.45384,0.74922,0.41922,0.7236,0.38278,0.58986,0.30721,0.48418,0.26477,0.43826,0.24633,0.2872,0.19418,0.14397,0.15864,0.01084,0.11598,0.01169,0.03096,0.04877,0.00736],"triangles":[29,30,9,30,8,9,30,31,8,31,7,8,31,32,7,32,6,7,32,5,6,32,33,5,5,33,4,33,34,4,34,3,4,34,35,3,36,2,35,35,2,3,37,1,36,36,1,2,37,0,1,37,38,0,0,39,40,0,38,39,16,17,21,17,18,19,19,20,21,21,17,19,21,22,16,16,22,15,22,23,15,23,24,15,15,24,14,13,14,25,14,24,25,13,25,12,12,25,26,26,27,12,12,27,11,27,28,11,11,28,10,28,29,10,29,9,10],"vertices":[2,13,18.55,-101.53,0.0001,12,-39.43,-8.95,0.9999,2,13,15.72,-94.36,0.00056,12,-32.07,-6.63,0.99944,2,13,-7.46,-48.51,0.00241,12,16.32,10.84,0.99759,2,13,-10.27,-38.26,0.00833,12,26.74,12.93,0.99167,2,13,-11.41,-34.11,0.02395,12,30.96,13.77,0.97605,2,13,-12.65,-23.12,0.0583,12,42.01,14.24,0.9417,2,13,-12.06,-13.95,0.12194,12,51.12,13.01,0.87806,2,13,-11.72,-8.52,0.22209,12,56.51,12.28,0.77791,2,13,-8.64,-2.04,0.35671,12,62.76,8.76,0.64329,2,13,-2.78,3.21,0.51182,12,67.59,2.55,0.48818,2,13,5.35,10.52,0.66522,12,74.31,-6.08,0.33478,2,13,15.94,12.47,0.79539,12,75.51,-16.77,0.20461,2,13,24.95,11.98,0.89,12,74.39,-25.72,0.11,2,13,34.93,11.43,0.94866,12,73.14,-35.64,0.05134,2,13,42.12,9.59,0.97949,12,70.8,-42.69,0.02051,2,13,50.54,7.43,0.9931,12,68.06,-50.93,0.0069,2,13,54.09,6.52,0.99808,12,66.9,-54.41,0.00192,2,13,58.93,4.36,0.99957,12,64.41,-59.09,0.00043,2,13,62.4,0.46,0.99991,12,60.28,-62.28,0.00009,2,13,62.11,-4.04,0.99997,12,55.8,-61.68,0.00003,2,13,58.18,-7.52,0.99991,12,52.61,-57.51,0.00009,2,13,54.07,-7.35,0.99957,12,53.07,-53.43,0.00043,2,13,49.93,-6.22,0.99808,12,54.48,-49.38,0.00192,2,13,46.54,-5.3,0.9931,12,55.64,-46.05,0.0069,2,13,40.18,-3.56,0.97949,12,57.82,-39.83,0.02051,2,13,31.09,-1.09,0.94866,12,60.92,-30.94,0.05134,2,13,25.8,-0.77,0.89001,12,61.61,-25.68,0.10999,2,13,19.93,-0.41,0.79539,12,62.38,-19.85,0.20461,2,13,11.09,-2.91,0.66522,12,60.5,-10.86,0.33478,2,13,5.14,-4.6,0.51182,12,59.24,-4.8,0.48818,2,13,3.58,-8.12,0.35672,12,55.84,-3,0.64328,2,13,2.16,-11.31,0.22208,12,52.75,-1.36,0.77792,2,13,0.67,-14.67,0.12194,12,49.5,0.36,0.87806,2,13,0.75,-25.19,0.0583,12,39.01,1.02,0.9417,2,13,2,-32.44,0.02396,12,31.69,0.28,0.97604,2,13,2.54,-35.59,0.00833,12,28.51,-0.04,0.99167,2,13,4.91,-45.43,0.00241,12,18.52,-1.71,0.99759,2,13,29.36,-92.71,0.00056,12,-31.39,-20.35,0.99944,2,13,31.67,-101.18,0.0001,12,-40,-22.06,0.9999,2,13,25.81,-106.36,0.00002,12,-44.75,-15.85,0.99998,2,13,22.73,-106.18,0.00002,12,-44.36,-12.8,0.99998],"edges":[0,80,0,2,8,10,14,16,20,22,32,34,34,36,36,38,38,40,40,42,64,66,70,72,72,74,74,76,76,78,78,80,0,76,74,2,2,4,72,4,4,6,6,8,70,6,66,68,68,70,8,68,66,10,10,12,12,14,64,12,62,64,62,14,58,60,60,62,16,60,16,18,18,20,58,18,54,56,56,58,56,20,22,54,50,52,52,54,22,24,24,26,52,24,50,26,26,28,48,50,28,48,46,48,28,30,30,32,46,30,42,34,42,44,44,46,32,44]}},"dau":{"dau":{"x":128.77,"y":-3.29,"rotation":-91.68,"width":376,"height":322},"dau1":{"x":125.03,"y":-2.15,"rotation":-91.68,"width":377,"height":322}},"eye_L":{"eye_L":{"x":5.37,"y":-8.63,"rotation":-91.68,"width":131,"height":156},"eye_L1":{"x":47.21,"y":28.69,"rotation":-91.68,"width":45,"height":67}},"eye_R":{"eye_R":{"x":4.96,"y":12.95,"rotation":-91.68,"width":131,"height":156},"eye_R1":{"x":39.57,"y":-8.55,"rotation":-91.68,"width":43,"height":68}},"long den p":{"long den p":{"x":0.11,"y":0.06,"rotation":-91.68,"width":38,"height":55}},"long den t":{"long den t":{"x":2.59,"y":-1.39,"rotation":-91.68,"width":38,"height":55}},"long may p":{"long may p":{"x":-12.1,"y":-1.19,"rotation":-91.68,"width":49,"height":42}},"long may t":{"long may t":{"x":-11.5,"y":-3.88,"rotation":-91.68,"width":57,"height":45}},"mieng":{"mieng":{"x":3.74,"y":-1.78,"rotation":-91.68,"width":250,"height":158},"mieng 1":{"x":86.55,"y":-0.19,"rotation":-91.68,"width":321,"height":205}},"tay p":{"tay p":{"type":"mesh","hull":26,"width":73,"height":167,"uvs":[0.94752,0.00409,0.99078,0.02306,0.99129,0.05573,0.83609,0.11979,0.69939,0.17621,0.53035,0.26998,0.4699,0.31701,0.35506,0.40635,0.26243,0.51367,0.23002,0.58758,0.18269,0.69551,0.20176,0.85071,0.21051,0.92191,0.20982,0.99514,0.09302,0.99713,0.05061,0.97596,0.00946,0.85159,0.00871,0.6696,0.04833,0.56791,0.08864,0.46448,0.20792,0.35862,0.30617,0.27142,0.40286,0.21348,0.49709,0.15702,0.69485,0.07076,0.84905,0.00351],"triangles":[19,20,7,7,20,6,20,21,6,6,21,5,21,22,5,22,23,5,5,23,4,23,24,4,4,24,3,1,2,0,0,2,25,25,2,3,3,24,25,13,14,12,12,14,15,12,16,11,12,15,16,16,10,11,16,17,10,10,17,9,17,18,9,9,18,8,18,19,8,8,19,7],"vertices":[2,4,-97.27,78.65,0.02148,3,-35.47,8.43,0.97852,2,4,-94.19,81.89,0.02148,3,-34.82,12.86,0.97852,2,4,-88.74,82.08,0.03387,3,-30.46,16.14,0.96613,2,4,-57.58,46.65,0.06078,3,15.4,5.07,0.93922,2,4,-43.81,34.83,0.11151,3,33.46,3.31,0.88849,2,4,-35.6,28.14,0.18986,3,44.02,2.55,0.81014,2,4,-23.93,20.82,0.29561,3,57.78,3.28,0.70439,2,4,-8.79,12.84,0.42221,3,74.76,5.46,0.57779,2,4,9.31,6.57,0.5572,3,93.17,10.73,0.4428,2,4,21.71,4.54,0.68534,3,104.49,16.19,0.31466,2,4,39.82,1.57,0.79305,3,121.01,24.18,0.20695,2,4,65.69,3.66,0.87175,3,140.98,40.76,0.12825,2,4,77.56,4.62,0.9184,3,150.14,48.37,0.0816,2,4,89.79,4.9,0.94135,3,159.98,55.63,0.05865,2,4,90.35,-3.61,0.94135,3,165.34,48.99,0.05865,2,4,86.9,-6.8,0.91839,3,164.35,44.39,0.08161,2,4,66.22,-10.37,0.87175,3,149.48,29.59,0.12825,2,4,40.4,-10.51,0.79305,3,128.43,14.63,0.20695,2,4,18.79,-8.81,0.68534,3,109.77,3.59,0.31466,2,4,1.44,-6.34,0.5572,3,94.15,-4.36,0.4428,2,4,-14.44,0.62,0.42221,3,77.16,-7.8,0.57779,2,4,-31.22,8.67,0.29561,3,58.81,-10.86,0.70439,2,4,-41.08,15.46,0.18986,3,46.83,-10.97,0.81014,2,4,-50.69,22.08,0.11151,3,35.16,-11.07,0.88849,2,4,-65.48,36.12,0.06078,3,14.99,-8.09,0.93922,2,4,-97.18,71.46,0.03387,3,-31.26,2.61,0.96613],"edges":[0,50,0,2,2,4,8,10,14,16,24,26,26,28,28,30,30,32,32,34,8,46,10,12,12,14,42,12,38,16,34,20,20,22,22,24,32,22,34,36,36,38,16,18,18,20,36,18,38,40,40,42,14,40,42,44,44,46,10,44,46,48,48,50,4,6,6,8,48,6]}},"tay t":{"tay t":{"type":"mesh","hull":28,"width":78,"height":155,"uvs":[0.30638,0.07811,0.43627,0.1512,0.54173,0.21053,0.64535,0.30129,0.73227,0.37741,0.8046,0.46478,0.86881,0.54236,0.90202,0.62206,0.94285,0.72004,0.99078,0.83506,0.99196,0.9755,0.95047,0.99567,0.86288,0.99559,0.82923,0.96181,0.80789,0.84449,0.7695,0.72551,0.72966,0.64513,0.68827,0.56162,0.63308,0.49415,0.5709,0.41812,0.48676,0.34423,0.40314,0.27079,0.29667,0.20945,0.17872,0.14149,0.00862,0.06019,0.00331,0.02802,0.01779,0.00433,0.13283,0.00424],"triangles":[18,19,5,19,4,5,19,3,4,19,20,3,20,21,3,21,2,3,21,1,2,21,22,1,22,23,1,23,0,1,23,24,27,27,25,26,23,27,0,27,24,25,10,11,13,11,12,13,13,9,10,13,14,9,14,8,9,14,15,8,8,15,7,15,16,7,16,17,7,17,6,7,17,5,6,17,18,5],"vertices":[2,7,-67.89,-22.95,0.01043,6,17.19,9.87,0.98957,2,7,-55.04,-14.83,0.0317,6,32.31,11.38,0.9683,2,7,-44.61,-8.24,0.0796,6,44.59,12.6,0.9204,2,7,-29.4,-2.6,0.1672,6,60.72,10.84,0.8328,2,7,-16.64,2.14,0.29912,6,74.25,9.36,0.70088,2,7,-2.35,5.46,0.46396,6,88.51,5.94,0.53604,2,7,10.33,8.41,0.63531,6,101.18,2.9,0.36469,2,7,22.94,8.92,0.78357,6,112.69,-2.29,0.21643,2,7,38.45,9.55,0.88986,6,126.83,-8.67,0.11014,2,7,56.65,10.29,0.95219,6,143.44,-16.16,0.04781,2,7,78.13,6.78,0.98038,6,161.08,-28.91,0.01962,2,7,80.68,3.07,0.99174,6,161.7,-33.37,0.00826,2,7,79.54,-3.67,0.99173,6,157.66,-38.88,0.00827,2,7,73.94,-5.39,0.98037,6,151.88,-37.92,0.01963,2,7,55.73,-4.02,0.95218,6,136.21,-28.54,0.04782,2,7,37.05,-3.92,0.88985,6,119.55,-20.09,0.11015,2,7,24.25,-4.93,0.78356,6,107.65,-15.26,0.21644,2,7,10.95,-5.97,0.63531,6,95.29,-10.24,0.36469,2,7,-0.08,-8.49,0.46394,6,84.31,-7.55,0.53606,2,7,-12.5,-11.32,0.29912,6,71.93,-4.53,0.70088,2,7,-24.88,-15.9,0.16719,6,58.81,-3.08,0.83281,2,7,-37.19,-20.45,0.0796,6,45.77,-1.64,0.9204,2,7,-47.94,-27.06,0.03169,6,33.19,-2.74,0.96831,2,7,-59.85,-34.4,0.01043,6,19.26,-3.97,0.98957,2,7,-97.79,-62.88,0.00323,6,-27.42,-12.46,0.99677,2,7,-102.77,-62.47,0.00094,6,-31.69,-9.86,0.99906,2,7,-106.21,-60.75,0.00094,6,-33.99,-6.78,0.99906,2,7,-104.74,-51.89,0.00323,6,-28.71,0.48,0.99677],"edges":[0,54,18,20,20,22,22,24,24,26,48,50,50,52,52,54,46,48,0,46,4,42,8,38,12,34,16,18,30,16,26,28,18,28,28,30,42,44,44,46,0,2,2,4,44,2,38,40,40,42,4,6,6,8,40,6,8,10,10,12,34,36,36,38,10,36,30,32,32,34,12,14,14,16,32,14]}},"than":{"than":{"type":"mesh","hull":28,"width":191,"height":266,"uvs":[0.45099,0,0.35417,0.00889,0.25028,0.07671,0.17944,0.16657,0.11333,0.2683,0.0543,0.3819,0.02124,0.48363,0,0.56501,0,0.65976,0.01216,0.74623,0.05938,0.81744,0.11605,0.89543,0.19633,0.95138,0.30495,0.98868,0.42301,1,0.58594,1,0.77248,0.97681,0.91888,0.91069,0.9968,0.80387,1,0.69197,1,0.59363,0.97791,0.48682,0.92124,0.36983,0.84741,0.26132,0.77894,0.15789,0.71518,0.07312,0.62546,0.01886,0.52628,0,0.49559,0.12737,0.49559,0.27997,0.49559,0.4173,0.49086,0.55972,0.49323,0.6818,0.50267,0.80896,0.51448,0.90899],"triangles":[28,0,27,28,27,26,28,1,0,28,2,1,28,3,2,29,3,28,4,3,29,28,26,25,29,23,30,4,29,30,5,4,30,28,25,24,30,6,5,31,6,30,7,6,31,8,7,31,19,32,31,8,31,32,24,29,28,23,29,24,30,21,20,9,8,32,30,20,19,30,19,31,22,30,23,21,30,22,18,33,19,33,32,19,10,9,32,33,10,32,11,10,33,33,16,34,12,11,33,18,17,33,33,13,12,17,16,33,34,13,33,14,13,34,15,34,16,14,34,15],"vertices":[246.48,5.66,244.47,17.79,224.72,21.38,200.77,20.09,170.9,16.9,139.79,17.82,115.43,18.08,96.98,19.53,68.18,20.37,47.92,21.8,27.22,23.77,10.61,26.75,-3.35,27.54,-12.68,25.7,-20.27,14.79,-20.17,-12.29,-9.76,-21.62,5.53,-23.42,30.87,-21.01,59.82,-18.41,89.14,-18.82,116.16,-20.36,141.87,-20.66,170.71,-21.84,201.36,-23.2,226.18,-23.02,242.31,-20.06,246.05,-8.72,212.36,-1.86,171.79,-0.67,135.27,0.4,97.43,2.42,64.96,2.92,31.1,2.12,4.43,0.64],"edges":[0,2,2,4,4,6,6,8,8,10,10,12,12,14,14,16,16,18,18,20,20,22,22,24,24,26,26,28,28,30,30,32,32,34,34,36,36,38,38,40,40,42,42,44,44,46,46,48,48,50,50,52,52,54,0,54]}},"toc":{"toc":{"x":85.21,"y":1.29,"scaleX":0.7376,"scaleY":1.1099,"rotation":-90.64,"width":113,"height":78}}}}],"animations":{"finish":{"slots":{"eye_L":{"attachment":[{"time":0.1333,"name":"eye_L1"}]},"eye_R":{"attachment":[{"time":0.1333,"name":"eye_R1"}]},"long den p":{"attachment":[{"time":0.1333,"name":null}]},"long den t":{"attachment":[{"time":0.1333,"name":null}]},"long may p":{"attachment":[{"name":null},{"time":0.1333,"name":"long may p"}]},"long may t":{"attachment":[{"name":null},{"time":0.1333,"name":"long may t"}]},"mieng":{"attachment":[{"time":0.1333,"name":"mieng 1"}]}},"bones":{"bone":{"rotate":[{},{"time":0.1333,"angle":-9.67},{"time":0.3,"angle":-24.25},{"time":0.4667,"angle":-26.45,"curve":"stepped"},{"time":1.0333,"angle":-26.45},{"time":1.2,"angle":-7.41},{"time":1.3333}],"translate":[{"curve":0.269,"c3":0.618,"c4":0.42},{"time":0.0667,"y":-27.71,"curve":0.32,"c2":0.29,"c3":0.667,"c4":0.67},{"time":0.1333,"x":16.62,"y":41.86,"curve":0.349,"c2":0.39,"c3":0.689,"c4":0.74},{"time":0.3,"x":33.73,"y":34.96,"curve":0.375,"c2":0.62,"c3":0.716},{"time":0.4667,"x":25.86,"y":51.1,"curve":0.381,"c2":0.55,"c3":0.742},{"time":1.0333,"x":37.2,"y":62.44,"curve":0.381,"c2":0.55,"c3":0.742},{"time":1.2,"x":5.54,"y":-16.62,"curve":0.25,"c3":0.75},{"time":1.3333,"curve":0.25,"c3":0.75},{"time":1.6,"y":17.71,"curve":0.25,"c3":0.75},{"time":1.8333,"curve":0.25,"c3":0.75},{"time":2.1,"y":33.8,"curve":0.25,"c3":0.75},{"time":2.3333}]},"dau":{"rotate":[{"time":1.3333,"curve":0.25,"c3":0.75},{"time":1.8333,"angle":-12.1,"curve":0.25,"c3":0.75},{"time":2.3333}]},"tay p":{"rotate":[{"time":0.0667,"curve":0.245,"c3":0.637,"c4":0.56},{"time":0.1333,"angle":-47.73,"curve":"stepped"},{"time":1.2,"angle":-47.73,"curve":0.381,"c2":0.55,"c3":0.742},{"time":1.3333,"curve":0.25,"c3":0.75},{"time":1.6,"angle":-63.92,"curve":0.25,"c3":0.75},{"time":1.8333,"angle":-9.89,"curve":0.25,"c3":0.75},{"time":2.1,"angle":-33.99,"curve":0.25,"c3":0.75},{"time":2.3333}],"translate":[{"curve":0.245,"c3":0.637,"c4":0.56},{"time":0.1333,"x":28.74,"y":-3.46,"curve":"stepped"},{"time":1.2,"x":28.74,"y":-3.46,"curve":0.381,"c2":0.55,"c3":0.742},{"time":1.3333,"curve":0.305,"c3":0.64,"c4":0.36},{"time":1.4333,"x":11.15,"y":-22.8,"curve":0.304,"c2":0.2,"c3":0.642,"c4":0.56},{"time":1.6,"x":38.11,"y":-26.46,"curve":0.318,"c2":0.28,"c3":0.69,"c4":0.74},{"time":2.1,"x":26.68,"y":-13.79,"curve":0.349,"c2":0.4,"c3":0.684,"c4":0.74},{"time":2.2,"x":23.42,"y":-9.37,"curve":0.356,"c2":0.51,"c3":0.692,"c4":0.86},{"time":2.3,"x":8.28,"y":-4.49,"curve":0.344,"c2":0.66,"c3":0.677},{"time":2.3333}]},"tay p2":{"rotate":[{"curve":0.245,"c3":0.637,"c4":0.56},{"time":0.1333,"angle":-22.75,"curve":0.381,"c2":0.55,"c3":0.742},{"time":0.4667,"angle":-3.23,"curve":"stepped"},{"time":1.0333,"angle":-3.23,"curve":0.381,"c2":0.55,"c3":0.742},{"time":1.2,"angle":-5.11,"curve":"stepped"},{"time":1.3333,"angle":-5.11,"curve":0.363,"c2":0.44,"c3":0.755},{"time":1.5,"curve":0.25,"c3":0.75},{"time":1.7333,"angle":-75.31,"curve":0.25,"c3":0.75},{"time":2,"angle":-1.11,"curve":0.25,"c3":0.75},{"time":2.2333,"angle":-65.06,"curve":0.258,"c3":0.619,"c4":0.45},{"time":2.3333,"angle":-5.11}],"translate":[{},{"time":0.1333,"x":0.3,"y":-1.41},{"time":0.4667}]},"tay t":{"rotate":[{"time":0.0667,"curve":0.245,"c3":0.637,"c4":0.56},{"time":0.1333,"angle":32.51,"curve":0.381,"c2":0.55,"c3":0.742},{"time":0.4667,"angle":23.25,"curve":0.381,"c2":0.55,"c3":0.742},{"time":1.0333,"angle":40.27,"curve":0.381,"c2":0.55,"c3":0.742},{"time":1.2,"curve":"stepped"},{"time":1.3333,"curve":0.25,"c3":0.75},{"time":1.6,"angle":62.45,"curve":0.25,"c3":0.75},{"time":1.8333,"curve":0.25,"c3":0.75},{"time":2.1,"angle":33.81,"curve":0.25,"c3":0.75},{"time":2.3333}],"translate":[{"curve":0.245,"c3":0.637,"c4":0.56},{"time":0.1333,"x":19.45,"y":20.74,"curve":0.381,"c2":0.55,"c3":0.742},{"time":0.4667,"x":22.06,"y":21.94,"curve":0.381,"c2":0.55,"c3":0.742},{"time":1.0333,"x":19.79,"y":21.51,"curve":0.381,"c2":0.55,"c3":0.742},{"time":1.2,"x":20.74,"y":12.81,"curve":0.25,"c3":0.75},{"time":1.3333,"curve":0.305,"c3":0.64,"c4":0.36},{"time":1.4333,"x":7,"y":16.94,"curve":0.304,"c2":0.2,"c3":0.642,"c4":0.56},{"time":1.6,"x":25.3,"y":11.27,"curve":0.318,"c2":0.28,"c3":0.69,"c4":0.74},{"time":2.1,"x":13.77,"y":8.62,"curve":0.378,"c2":0.61,"c3":0.722},{"time":2.3333}]},"tay t2":{"rotate":[{},{"time":0.1333,"angle":25.12},{"time":0.4667,"angle":17.36,"curve":"stepped"},{"time":1.0333,"angle":17.36},{"time":1.2,"angle":28.94,"curve":"stepped"},{"time":1.3333,"angle":28.94,"curve":0.375,"c2":0.5,"c3":0.75},{"time":1.4667,"curve":0.25,"c3":0.75},{"time":1.7,"angle":46.55,"curve":0.25,"c3":0.75},{"time":1.9667,"curve":0.25,"c3":0.75},{"time":2.2,"angle":57.88,"curve":0.25,"c3":0.625,"c4":0.5},{"time":2.3333,"angle":28.94}],"translate":[{},{"time":0.1333,"x":25.89,"y":2.13},{"time":0.4667,"x":30.33,"y":-6.92},{"time":1.0333,"x":25.96,"y":-13.41},{"time":1.2,"x":24.35,"y":-1.16},{"time":1.3333}]},"chan p":{"rotate":[{"angle":1.11},{"time":0.1333,"angle":-21.43,"curve":"stepped"},{"time":1.0333,"angle":-21.43},{"time":1.2,"angle":1.11}]},"chan p2":{"rotate":[{"angle":-1.46},{"time":0.1333,"angle":-20.72,"curve":"stepped"},{"time":1.0333,"angle":-20.72},{"time":1.2,"angle":-1.46}]},"ban chan p":{"rotate":[{"angle":-0.89},{"time":0.1333,"angle":51.5,"curve":"stepped"},{"time":1.0333,"angle":51.5},{"time":1.2,"angle":-0.89}]},"chan t":{"rotate":[{"angle":2.5},{"time":0.1333,"angle":-22.11,"curve":"stepped"},{"time":1.0333,"angle":-22.11},{"time":1.2,"angle":2.5}]},"chan t2":{"rotate":[{"angle":-3.43},{"time":0.1333,"angle":47.01,"curve":"stepped"},{"time":1.0333,"angle":47.01},{"time":1.2,"angle":-3.43}]},"ban chan t":{"rotate":[{"angle":-0.98},{"time":0.1333,"angle":-17.2,"curve":"stepped"},{"time":1.0333,"angle":-17.2},{"time":1.2,"angle":-0.98}]},"mieng":{"rotate":[{},{"time":0.1,"angle":-6.18},{"time":0.1333}],"scale":[{"time":1.3333,"curve":0.273,"c3":0.62,"c4":0.41},{"time":1.6,"x":1.14,"curve":0.316,"c2":0.28,"c3":0.66,"c4":0.65},{"time":1.8667,"x":0.889,"curve":0.349,"c2":0.38,"c3":0.693,"c4":0.75},{"time":2.1333,"x":1.167,"curve":0.375,"c2":0.62,"c3":0.716},{"time":2.3333}]},"eye_R":{"translate":[{"time":1.3333},{"time":1.6333,"x":14.37,"y":-0.42},{"time":1.8333},{"time":2.1333,"x":14.37,"y":-0.42},{"time":2.3333}],"scale":[{"time":1.1333},{"time":1.2,"x":0.073},{"time":1.2667,"curve":"stepped"},{"time":1.3333},{"time":1.6333,"x":1.287},{"time":1.8333,"x":0.655},{"time":2.1333,"x":1.173},{"time":2.3333}]},"eye_L":{"translate":[{"time":1.3333},{"time":1.6333,"x":14.37,"y":-0.42},{"time":1.8333},{"time":2.1333,"x":14.37,"y":-0.42},{"time":2.3333}],"scale":[{"time":1.1333},{"time":1.2,"x":0.073},{"time":1.2667,"curve":"stepped"},{"time":1.3333},{"time":1.6333,"x":1.287},{"time":1.8333,"x":0.655},{"time":2.1333,"x":1.173},{"time":2.3333}]},"chan_p":{"rotate":[{"time":0.1333},{"time":0.3,"angle":-46.75,"curve":"stepped"},{"time":1.0333,"angle":-46.75},{"time":1.2}],"translate":[{"time":0.0667},{"time":0.1333,"x":-48.02,"y":66.49},{"time":0.3,"x":-56.06,"y":122.66},{"time":0.4667,"x":-30.86,"y":93.87},{"time":1.0333,"x":-19.52,"y":105.21},{"time":1.2}]},"eye_R3":{"translate":[{"x":5.93,"y":-0.17,"curve":"stepped"},{"time":1.3333,"x":5.93,"y":-0.17,"curve":0.38,"c2":0.59,"c3":0.727},{"time":1.4333,"curve":0.25,"c3":0.75},{"time":1.9333,"x":29.27,"y":-0.86,"curve":0.242,"c3":0.663,"c4":0.65},{"time":2.3333,"x":5.93,"y":-0.17}]},"eye_L3":{"translate":[{"x":5.93,"y":-0.17,"curve":"stepped"},{"time":1.3333,"x":5.93,"y":-0.17,"curve":0.38,"c2":0.59,"c3":0.727},{"time":1.4333},{"time":1.9333,"x":29.27,"y":-0.86,"curve":0.242,"c3":0.663,"c4":0.65},{"time":2.3333,"x":5.93,"y":-0.17}]}},"deform":{"default":{"chan t":{"chan t":[{"vertices":[-0.41061,1.96927,2.00591,0.15208,-0.41061,1.96927,2.00591,0.15208,0,0,0,0,0,0,0,0,0,0,0,0,0,0,0,0,0,0,0,0,0,0,0,0,0,0,0,0,0,0,0,0,0,0,0,0,0,0,0,0,0,0,0,0,0,0,0,0,0,0,0,0,0,0,0,0,0,0,0,0,0,0,0,0,0,0,0,0,0,0,0,0,0,0,0,0,0,0,0,0,0,0,0,0,0,0,0,0,0,0,0,0,0,0,0,0,0,0,0,0,0,0,0,0,0,0,0,0,0,0,0,0,0,0,0,0,0,0,0,0,0,0,0,0,0,0,0,0,0,0,0,0,0,0,0,0,0,0,0,0,-0.41061,1.96927,2.00591,0.15208,-0.41061,1.96927,2.00591,0.15208,-0.41061,1.96927,2.00591,0.15208,-0.41061,1.96927,2.00591,0.15208]},{"time":0.0667,"vertices":[5.40188,-29.64996,-4.17591,12.69503,2.75249,-29.39089,-5.79301,14.80963,0,0,0,0,0,0,0,0,0,0,0,0,0,0,0,0,0,0,0,0,0,0,0,0,0,0,0,0,0,0,0,0,0,0,0,0,0,0,0,0,0,0,0,0,0,0,0,0,0,0,0,0,0,0,0,0,0,0,0,0,0,0,0,0,0,0,0,0,0,0,0,0,0,0,0,0,0,0,0,0,0,0,0,0,0,0,0,0,0,0,0,0,0,0,0,0,0,0,0,0,0,0,0,0,0,0,0,0,0,0,0,0,0,0,0,0,0,0,0,0,0,0,0,0,0,0,0,0,0,0,0,0,0,0,0,0,0,0,0,0,4.36749,-24.94069,-1.43661,16.66284,7.33613,-25.55971,0.13488,14.06927,8.01715,-28.17177,-1.31139,11.79,7.48205,-29.08973,-2.34772,11.55548]},{"time":0.1333,"vertices":[30.71607,-4.77177,18.29986,-27.21243,25.4173,-4.25363,15.06566,-22.98322,0,0,0,0,0,0,0,0,0,0,0,0,0,0,0,0,0,0,0,0,0,0,0,0,0,0,0,0,0,0,0,0,0,0,0,0,0,0,0,0,0,0,0,0,0,0,0,0,0,0,0,0,0,0,0,0,0,0,0,0,0,0,0,0,0,0,0,0,0,0,0,0,0,0,0,0,0,0,0,0,0,0,0,0,0,0,0,0,0,0,0,0,0,0,0,0,0,0,0,0,0,0,0,0,0,0,0,0,0,0,0,0,0,0,0,0,0,0,0,0,0,0,0,0,0,0,0,0,0,0,0,0,0,0,0,0,0,0,0,0,28.64729,4.64677,23.77847,-19.27681,34.58457,3.40874,26.92144,-24.46394,35.94662,-1.81539,24.0289,-29.02248,34.8764,-3.65132,21.95624,-29.49152]},{"time":0.3667,"vertices":[15.67426,-11.13715,6.73509,-15.67879,10.37549,-10.61901,3.50089,-11.44958,0,0,0,0,0,0,0,0,0,0,0,0,0,0,0,0,0,0,0,0,0,0,0,0,0,0,0,0,0,0,0,0,0,0,0,0,0,0,0,0,0,0,0,0,0,0,0,0,0,0,0,0,0,0,0,0,0,0,0,0,0,0,0,0,0,0,0,0,0,0,0,0,0,0,0,0,0,0,0,0,0,0,0,0,0,0,0,0,0,0,0,0,0,0,0,0,0,0,0,0,0,0,0,0,0,0,0,0,0,0,0,0,0,0,0,0,0,0,0,0,0,0,0,0,0,0,0,0,0,0,0,0,0,0,0,0,0,0,0,0,13.60548,-1.71861,12.2137,-7.74317,19.54276,-2.95664,15.35666,-12.93031,20.90481,-8.18077,12.46412,-17.48885,19.83459,-10.01669,10.39147,-17.95788]},{"time":1.2,"vertices":[3.9274,-31.03068,-3.02141,5.26294,-1.37138,-30.51254,-6.25561,9.49215,0,0,0,0,0,0,0,0,0,0,0,0,0,0,0,0,0,0,0,0,0,0,0,0,0,0,0,0,0,0,0,0,0,0,0,0,0,0,0,0,0,0,0,0,0,0,0,0,0,0,0,0,0,0,0,0,0,0,0,0,0,0,0,0,0,0,0,0,0,0,0,0,0,0,0,0,0,0,0,0,0,0,0,0,0,0,0,0,0,0,0,0,0,0,0,0,0,0,0,0,0,0,0,0,0,0,0,0,0,0,0,0,0,0,0,0,0,0,0,0,0,0,0,0,0,0,0,0,0,0,0,0,0,0,0,0,0,0,0,0,1.85862,-21.61213,2.4572,13.19856,7.7959,-22.85016,5.60016,8.01143,9.15794,-28.0743,2.70762,3.45289,8.08773,-29.91022,0.63497,2.98386]},{"time":1.3333,"vertices":[-0.41061,1.96927,2.00591,0.15208,-0.41061,1.96927,2.00591,0.15208,0,0,0,0,0,0,0,0,0,0,0,0,0,0,0,0,0,0,0,0,0,0,0,0,0,0,0,0,0,0,0,0,0,0,0,0,0,0,0,0,0,0,0,0,0,0,0,0,0,0,0,0,0,0,0,0,0,0,0,0,0,0,0,0,0,0,0,0,0,0,0,0,0,0,0,0,0,0,0,0,0,0,0,0,0,0,0,0,0,0,0,0,0,0,0,0,0,0,0,0,0,0,0,0,0,0,0,0,0,0,0,0,0,0,0,0,0,0,0,0,0,0,0,0,0,0,0,0,0,0,0,0,0,0,0,0,0,0,0,0,-0.41061,1.96927,2.00591,0.15208,-0.41061,1.96927,2.00591,0.15208,-0.41061,1.96927,2.00591,0.15208,-0.41061,1.96927,2.00591,0.15208]},{"time":2.1,"vertices":[2.18464,-1.61219,0.48401,-2.67163,1.05768,-1.00547,0.08006,-1.45715,0,0,0,0,0,0,0,0,0,0,0,0,0,0,0,0,0,0,0,0,0,0,0,0,0,0,0,0,0,0,0,0,0,0,0,0,0,0,0,0,0,0,0,0,0,0,0,0,0,0,0,0,0,0,0,0,0,0,0,0,0,0,0,0,0,0,0,0,0,0,0,0,0,0,0,0,0,0,0,0,0,0,0,0,0,0,0,0,0,0,0,0,0,0,0,0,0,0,0,0,0,0,0,0,0,0,0,0,0,0,0,0,0,0,0,0,0,0,0,0,0,0,0,0,0,0,0,0,0,0,0,0,0,0,0,0,0,0,0,0,1.87266,-2.46172,-0.32571,-3.07582,1.33518,-1.30017,0.0799,-1.86195,1.35277,-4.50742,-2.10715,-4.20791,0.62418,-0.19065,0.32346,-0.56686]}]},"tay p":{"tay p":[{"offset":100,"vertices":[-0.37985,-0.0103,-0.30492,-0.22681]},{"time":0.1333,"curve":"stepped","vertices":[25.02605,-27.77332,20.89495,-14.59781,26.17415,-28.72366,22.30598,-15.05618,25.94514,-30.7142,22.87505,-17.03958,12.38269,-11.64395,7.95937,-2.61688,7.45876,-8.09006,3.53916,-0.8475,6.36053,-6.72272,3.03954,-0.42438,3.26841,-6.40198,0.99992,-1.54788,1.92695,-4.50516,0.39061,-0.80103,1.67913,-2.97446,0.79778,-0.10611,1.14208,-3.20343,0.9171,-1.12021,0.76176,-3.25757,1.03652,-1.81262,0.78571,-3.04068,1.31246,-1.96475,0.59783,-2.22519,1.03387,-1.48679,0.48922,-1.82632,0.88261,-1.25909,0.32587,-1.87427,0.74797,-1.36414,0.34341,-2.5448,0.91454,-1.87888,0.19291,-3.18726,0.81351,-2.3208,-0.06347,-3.45987,0.34195,-2.30634,-0.31757,-3.14563,-0.46339,-1.6055,-0.42317,-2.10455,-1.47857,-0.07211,-0.00576,-3.52649,-1.70618,-0.68677,2.04796,-3.84598,-0.80411,0.1431,2.85137,-4.76346,-0.80582,0.12405,4.60797,-6.12985,0.26981,-0.2471,8.83598,-9.37247,3.84288,-1.81531,22.26569,-28.19009,18.54408,-16.05374]},{"time":1.2,"vertices":[25.02605,-27.77332,20.89495,-14.59781,26.17415,-28.72366,22.30598,-15.05618,25.94514,-30.7142,22.87505,-17.03958,12.38269,-11.64395,7.95937,-2.61688,7.45876,-8.09006,3.53916,-0.8475,6.36053,-6.72272,3.03954,-0.42438,3.26841,-6.40198,0.99992,-1.54788,1.92695,-4.50516,0.39061,-0.80103,1.67913,-2.97446,0.79778,-0.10611,1.14208,-3.20343,0.9171,-1.12021,0.76176,-3.25757,1.03652,-1.81262,0.78571,-3.04068,1.31246,-1.96475,0.59783,-2.22519,1.03387,-1.48679,0.48922,-1.82632,0.88261,-1.25909,0.32587,-1.87427,0.74797,-1.36414,0.34341,-2.5448,0.91454,-1.87888,0.19291,-3.18726,0.81351,-2.3208,-0.06347,-3.45987,0.34195,-2.30634,-0.31757,-3.14563,-0.46339,-1.6055,-0.42317,-2.10455,-1.47857,-0.07211,-0.00576,-3.52649,-1.70618,-0.68677,2.04796,-3.84598,-0.80411,0.1431,2.85137,-4.76346,-0.80582,0.12405,4.60797,-6.12985,0.26981,-0.2471,8.83598,-9.37247,3.84288,-1.81531,22.26569,-28.19009,18.54408,-16.05374]},{"time":1.3333,"vertices":[-0.05405,-6.67114,-11.37442,-8.85237,1.09406,-7.62149,-9.96339,-9.31075,0.86505,-9.61203,-9.39431,-11.29414,12.38269,-11.64395,7.95937,-2.61688,7.45876,-8.09006,3.53916,-0.8475,6.36053,-6.72272,3.03954,-0.42438,3.26841,-6.40198,0.99992,-1.54788,1.92695,-4.50516,0.39061,-0.80103,1.67913,-2.97446,0.79778,-0.10611,1.14208,-3.20343,0.9171,-1.12021,0.76176,-3.25757,1.03652,-1.81262,0.78571,-3.04068,1.31246,-1.96475,0.59783,-2.22519,1.03387,-1.48679,0.48922,-1.82632,0.88261,-1.25909,0.32587,-1.87427,0.74797,-1.36414,0.34341,-2.5448,0.91454,-1.87888,0.19291,-3.18726,0.81351,-2.3208,-0.06347,-3.45987,0.34195,-2.30634,-0.31757,-3.14563,-0.46339,-1.6055,-0.42317,-2.10455,-1.47857,-0.07211,-0.00576,-3.52649,-1.70618,-0.68677,2.04796,-3.84598,-0.80411,0.1431,2.85137,-4.76346,-0.80582,0.12405,4.60797,-6.12985,0.26981,-0.2471,8.83598,-9.37247,3.84288,-1.81531,-2.81441,-7.08792,-13.72528,-10.3083]}]},"tay t":{"tay t":[{"offset":96,"vertices":[-1.22078,-7.27827,-4.34979,-5.96227,-1.22078,-7.27827,-4.34979,-5.96227,-1.22078,-7.27827,-4.34979,-5.96227,-1.22078,-7.27827,-4.34979,-5.96227]},{"time":0.1333,"vertices":[25.82848,0.46561,24.63342,-3.67166,25.14536,-1.42322,24.04458,-5.4437,23.48639,-0.02014,22.5582,-3.81094,21.13231,1.55164,20.42992,-1.87378,17.68933,2.27118,17.1825,-0.60583,13.59283,2.48538,13.27023,0.27829,9.29032,2.11063,9.10727,0.60504,5.61306,1.49161,5.52473,0.58932,2.92437,0.93723,2.89487,0.47186,1.30619,0.50833,1.30196,0.30289,0.56532,0.25668,0.56741,0.1698,0.24317,0.10922,0.24409,0.07184,0.24995,0.10547,0.25062,0.06775,0.59191,0.23471,0.59212,0.14554,1.39089,0.46939,1.38295,0.25656,3.1049,0.84674,3.0666,0.36578,6.0068,1.38556,5.90782,0.4491,9.96818,1.89691,9.76406,0.33298,14.60297,2.30585,14.26076,0.01132,19.02502,2.23224,18.50933,-0.76099,22.71652,1.56427,22.00828,-1.99921,25.21948,0.39008,24.31932,-3.55383,26.95786,-1.02689,25.88342,-5.20731,27.61763,1.02493,26.46334,-3.27136,21.18921,12.41301,16.96526,9.37682,21.00517,11.77492,16.72439,8.75352,20.64195,11.40309,16.33022,8.41508,19.49062,11.97096,15.23584,9.08507]},{"time":0.4667,"vertices":[50.33167,4.16928,49.93253,-3.9397,53.008,2.32635,52.14776,-6.21057,51.18436,0.43246,49.97015,-7.80573,46.99229,-0.08459,45.69285,-7.63565,39.45272,0.89383,38.44337,-5.45526,30.23811,1.43201,29.53112,-3.43063,20.61488,1.39398,20.17024,-1.91815,12.33376,1.06619,12.09016,-0.90826,6.34482,0.72064,6.2362,-0.29025,2.79105,0.41449,2.75238,-0.02795,1.17444,0.21841,1.16234,0.03424,0.49969,0.09299,0.49463,0.01471,0.50719,0.08914,0.50175,0.01056,1.20172,0.19617,1.18771,0.0097,2.87603,0.37558,2.83366,-0.07431,6.5249,0.63004,6.40747,-0.39658,12.72791,0.96002,12.47363,-1.0488,21.29265,1.18036,20.82696,-2.19025,31.24855,1.25238,30.52188,-3.69772,40.78844,0.85516,39.77013,-5.61026,48.57682,-0.07217,47.27145,-7.76126,52.91763,0.84259,51.73137,-7.54877,54.82056,2.7226,53.98663,-5.97418,52.12082,4.72867,51.76249,-3.53934,30.27348,10.86217,29.69923,7.21004,30.16013,10.21956,29.52756,6.57097,29.79698,9.84749,29.13331,6.23222,28.57454,10.42015,27.96952,6.91841]},{"time":1.0333,"vertices":[70.12646,6.53281,69.84978,-4.78,75.06369,0.74246,73.66364,-11.30978,75.22972,-2.45261,73.24128,-14.50854,68.2747,-3.21893,66.19675,-14.14124,58.15148,-3.29468,56.22816,-12.58704,44.76261,-2.39999,43.25283,-9.54117,30.74613,-1.91589,29.63924,-6.80899,18.34662,-0.89862,17.70977,-3.8111,9.40475,-0.27954,9.09583,-1.76743,4.11958,-0.02008,3.99366,-0.66919,1.7196,0.03964,1.6714,-0.22891,0.72961,0.01743,0.70918,-0.0961,0.73721,0.01328,0.71635,-0.10052,1.7474,0.01758,1.69731,-0.25327,4.2049,-0.05893,4.07533,-0.7157,9.58504,-0.37021,9.26734,-1.87381,18.74107,-1.00467,18.09357,-3.95157,31.73547,-1.14218,30.76183,-6.15634,45.53821,-2.01886,44.10175,-9.21719,59.4876,-3.33298,57.55537,-12.74182,69.85959,-3.20657,67.77577,-14.26694,76.96304,-2.04254,75.00256,-14.2515,76.87657,1.13843,75.50278,-11.07358,67.313,7.05405,67.13058,-3.67932,31.80544,12.27394,31.43729,8.35899,31.7555,11.61052,31.32484,7.68922,31.39215,11.23891,30.9305,7.35097,30.10649,11.83195,29.7076,8.06734]},{"time":1.2,"vertices":[39.12841,13.46138,34.22832,-1.75937,36.50245,10.23283,32.06956,-4.67233,31.49541,8.76729,27.49586,-5.48181,21.93787,7.76794,18.53269,-5.38297,75.94394,-6.98088,73.70956,-15.67044,58.14751,-4.59036,56.50347,-11.24301,39.60312,-2.70302,38.52062,-7.2328,23.60329,-1.36566,22.98075,-4.06264,12.08006,-0.51697,11.77824,-1.89531,5.28118,-0.12302,5.15809,-0.72472,2.19653,-0.00226,2.14926,-0.25151,0.93063,-0.00003,0.91039,-0.10547,0.93848,-0.00421,0.91776,-0.11,2.22458,-0.02443,2.17546,-0.27591,5.36687,-0.16193,5.24015,-0.77119,12.26051,-0.60773,11.9499,-2.00177,-46.67454,14.36086,-47.89981,8.71948,-29.08398,14.24609,-30.83514,6.80051,-12.09977,11.80193,-14.38526,2.12711,4.62419,9.73749,1.75294,-2.06053,18.08002,8.77924,14.63264,-4.73354,27.57182,9.14757,23.60635,-5.48636,32.69894,10.8114,28.28955,-4.48358,35.35782,13.76376,30.51368,-1.8436,34.26826,20.50822,24.84791,5.7261,35.47892,21.36906,25.93249,6.63107,36.43031,21.7794,26.81976,7.12794,37.74605,20.04056,28.29155,5.62088]},{"time":1.3333,"offset":96,"vertices":[-1.22078,-7.27827,-4.34979,-5.96227,-1.22078,-7.27827,-4.34979,-5.96227,-1.22078,-7.27827,-4.34979,-5.96227,-1.22078,-7.27827,-4.34979,-5.96227]}]}}}},"idle":{"slots":{"long may p":{"attachment":[{"name":null}]},"long may t":{"attachment":[{"name":null}]}},"bones":{"chan p":{"rotate":[{"angle":1.11}]},"chan p2":{"rotate":[{"angle":-1.46}]},"ban chan p":{"rotate":[{"angle":-0.89}]},"chan t":{"rotate":[{"angle":2.5}]},"chan t2":{"rotate":[{"angle":-3.43}]},"ban chan t":{"rotate":[{"angle":-0.98}]},"eye_R3":{"translate":[{"x":5.93,"y":-0.17}]},"eye_L3":{"translate":[{"x":5.93,"y":-0.17}]}}}}},[0]]],0,0,[0],[-1],[0]]